README.md
setup.py
unix_time/__init__.py
unix_time.egg-info/PKG-INFO
unix_time.egg-info/SOURCES.txt
unix_time.egg-info/dependency_links.txt
unix_time.egg-info/top_level.txt