Metadata-Version: 2.1
Name: unix-time
Version: 1.0.0
Summary: Unix timestamp made easy.
Home-page: https://github.com/tallesl/py-unix-time
Author: Talles Lasmar
Author-email: talleslasmar@gmail.com
License: UNKNOWN
Platform: UNKNOWN
